README.md
setup.py
mitmstatic/__init__.py
mitmstatic.egg-info/PKG-INFO
mitmstatic.egg-info/SOURCES.txt
mitmstatic.egg-info/dependency_links.txt
mitmstatic.egg-info/entry_points.txt
mitmstatic.egg-info/requires.txt
mitmstatic.egg-info/top_level.txt