Metadata-Version: 1.1
Name: mitmstatic
Version: 0.99.1
Summary: dms file dumper (for mitmproxy/mitmweb)
Home-page: https://polymath.tech
Author: David Preece
Author-email: davep@polymath.tech
License: BSD
Keywords: mitmproxy mitmdump mitmweb dms html http static
Platform: UNKNOWN
Classifier: Development Status :: 5 - Production/Stable
Classifier: Intended Audience :: Developers
Classifier: Intended Audience :: Information Technology
Classifier: Intended Audience :: System Administrators
Classifier: License :: OSI Approved :: BSD License
Classifier: Natural Language :: English
Classifier: Programming Language :: Python :: 3.4
Classifier: Programming Language :: Python :: 3.5
Classifier: Programming Language :: Python :: 3.6
